[
  {
    "route": "/transactions/[reference]",
    "firstLoadUncompressedJsBytes": 572797,
    "firstLoadChunkPaths": [
      ".next\\static\\chunks\\08m9clm752lym.js",
      ".next\\static\\chunks\\1cv950j51ghkk.js",
      ".next\\static\\chunks\\1waa6f1lc7ee1.js",
      ".next\\static\\chunks\\0xj8rswc3alam.js",
      ".next\\static\\chunks\\1gcwxsl3hdfy0.js",
      ".next\\static\\chunks\\1iybkuim8d8q9.js",
      ".next\\static\\chunks\\0cfq0vvr8ssds.js",
      ".next\\static\\chunks\\3hz5xha9-117e.js",
      ".next\\static\\chunks\\turbopack-0no1il3ho-nuk.js"
    ]
  },
  {
    "route": "/transactions",
    "firstLoadUncompressedJsBytes": 557979,
    "firstLoadChunkPaths": [
      ".next\\static\\chunks\\08m9clm752lym.js",
      ".next\\static\\chunks\\1cv950j51ghkk.js",
      ".next\\static\\chunks\\1waa6f1lc7ee1.js",
      ".next\\static\\chunks\\2l3_rvs2eyl0j.js",
      ".next\\static\\chunks\\1gcwxsl3hdfy0.js",
      ".next\\static\\chunks\\1iybkuim8d8q9.js",
      ".next\\static\\chunks\\0cfq0vvr8ssds.js",
      ".next\\static\\chunks\\3hz5xha9-117e.js",
      ".next\\static\\chunks\\turbopack-0no1il3ho-nuk.js"
    ]
  },
  {
    "route": "/",
    "firstLoadUncompressedJsBytes": 553345,
    "firstLoadChunkPaths": [
      ".next\\static\\chunks\\08m9clm752lym.js",
      ".next\\static\\chunks\\1cv950j51ghkk.js",
      ".next\\static\\chunks\\1waa6f1lc7ee1.js",
      ".next\\static\\chunks\\2rei-xy961dfn.js",
      ".next\\static\\chunks\\1gcwxsl3hdfy0.js",
      ".next\\static\\chunks\\1iybkuim8d8q9.js",
      ".next\\static\\chunks\\0cfq0vvr8ssds.js",
      ".next\\static\\chunks\\3hz5xha9-117e.js",
      ".next\\static\\chunks\\turbopack-0no1il3ho-nuk.js"
    ]
  },
  {
    "route": "/platform",
    "firstLoadUncompressedJsBytes": 552253,
    "firstLoadChunkPaths": [
      ".next\\static\\chunks\\08m9clm752lym.js",
      ".next\\static\\chunks\\1cv950j51ghkk.js",
      ".next\\static\\chunks\\1waa6f1lc7ee1.js",
      ".next\\static\\chunks\\42eaeyyzp431j.js",
      ".next\\static\\chunks\\1gcwxsl3hdfy0.js",
      ".next\\static\\chunks\\1iybkuim8d8q9.js",
      ".next\\static\\chunks\\0cfq0vvr8ssds.js",
      ".next\\static\\chunks\\3hz5xha9-117e.js",
      ".next\\static\\chunks\\turbopack-0no1il3ho-nuk.js"
    ]
  },
  {
    "route": "/monitoring",
    "firstLoadUncompressedJsBytes": 549820,
    "firstLoadChunkPaths": [
      ".next\\static\\chunks\\08m9clm752lym.js",
      ".next\\static\\chunks\\1cv950j51ghkk.js",
      ".next\\static\\chunks\\1waa6f1lc7ee1.js",
      ".next\\static\\chunks\\1dtyeu-ovy0yw.js",
      ".next\\static\\chunks\\1gcwxsl3hdfy0.js",
      ".next\\static\\chunks\\1iybkuim8d8q9.js",
      ".next\\static\\chunks\\0cfq0vvr8ssds.js",
      ".next\\static\\chunks\\3hz5xha9-117e.js",
      ".next\\static\\chunks\\turbopack-0no1il3ho-nuk.js"
    ]
  },
  {
    "route": "/reports",
    "firstLoadUncompressedJsBytes": 549394,
    "firstLoadChunkPaths": [
      ".next\\static\\chunks\\08m9clm752lym.js",
      ".next\\static\\chunks\\1cv950j51ghkk.js",
      ".next\\static\\chunks\\1waa6f1lc7ee1.js",
      ".next\\static\\chunks\\2ffsvxaldwdva.js",
      ".next\\static\\chunks\\1gcwxsl3hdfy0.js",
      ".next\\static\\chunks\\1iybkuim8d8q9.js",
      ".next\\static\\chunks\\0cfq0vvr8ssds.js",
      ".next\\static\\chunks\\3hz5xha9-117e.js",
      ".next\\static\\chunks\\turbopack-0no1il3ho-nuk.js"
    ]
  },
  {
    "route": "/profile",
    "firstLoadUncompressedJsBytes": 546853,
    "firstLoadChunkPaths": [
      ".next\\static\\chunks\\08m9clm752lym.js",
      ".next\\static\\chunks\\1cv950j51ghkk.js",
      ".next\\static\\chunks\\1waa6f1lc7ee1.js",
      ".next\\static\\chunks\\0fisi1f_hllwy.js",
      ".next\\static\\chunks\\1gcwxsl3hdfy0.js",
      ".next\\static\\chunks\\1iybkuim8d8q9.js",
      ".next\\static\\chunks\\0cfq0vvr8ssds.js",
      ".next\\static\\chunks\\3hz5xha9-117e.js",
      ".next\\static\\chunks\\turbopack-0no1il3ho-nuk.js"
    ]
  },
  {
    "route": "/_not-found",
    "firstLoadUncompressedJsBytes": 542811,
    "firstLoadChunkPaths": [
      ".next\\static\\chunks\\08m9clm752lym.js",
      ".next\\static\\chunks\\1cv950j51ghkk.js",
      ".next\\static\\chunks\\1waa6f1lc7ee1.js",
      ".next\\static\\chunks\\1gcwxsl3hdfy0.js",
      ".next\\static\\chunks\\1iybkuim8d8q9.js",
      ".next\\static\\chunks\\0cfq0vvr8ssds.js",
      ".next\\static\\chunks\\3hz5xha9-117e.js",
      ".next\\static\\chunks\\turbopack-0no1il3ho-nuk.js"
    ]
  }
]